setup.py
instaclone/__init__.py
instaclone/archives.py
instaclone/configs.py
instaclone/instaclone.py
instaclone/log_calls.py
instaclone/main.py
instaclone.egg-info/PKG-INFO
instaclone.egg-info/SOURCES.txt
instaclone.egg-info/dependency_links.txt
instaclone.egg-info/entry_points.txt
instaclone.egg-info/requires.txt
instaclone.egg-info/top_level.txt